cpraa/.git/COMMIT_EDITMSG
cpraa/.git/HEAD
cpraa/.git/config
cpraa/.git/description
cpraa/.git/hooks/applypatch-msg.sample
cpraa/.git/hooks/commit-msg.sample
cpraa/.git/hooks/post-update.sample
cpraa/.git/hooks/pre-applypatch.sample
cpraa/.git/hooks/pre-commit.sample
cpraa/.git/hooks/pre-push.sample
cpraa/.git/hooks/pre-rebase.sample
cpraa/.git/hooks/prepare-commit-msg.sample
cpraa/.git/hooks/update.sample
cpraa/.git/index
cpraa/.git/info/exclude
cpraa/.git/logs/HEAD
cpraa/.git/logs/refs/heads/master
cpraa/.git/logs/refs/remotes/origin/HEAD
cpraa/.git/logs/refs/remotes/origin/master
cpraa/.git/objects/00/67bf3a02306b806312a9c2b29ebbdbd7b150cd
cpraa/.git/objects/03/d794af89c1553775e93d0a22851ac4aeaa96ca
cpraa/.git/objects/03/f4d80017be882fac2ebf34cbcef72e38490fed
cpraa/.git/objects/04/6c01a460dcfe7eae88f15f58192b640552a0a5
cpraa/.git/objects/0d/bf5302494bbc5f06ed712fdd3e515b4e5f42ed
cpraa/.git/objects/0f/542be787b91d0a506e67bb2cb9ac0d86bf9278
cpraa/.git/objects/12/9e14681acd0d23548913c9089e202c8a2bb911
cpraa/.git/objects/13/ab9131c31f2c0b902698ede05e89876cce42ee
cpraa/.git/objects/14/965a62d1027198b3827e02bb355f10a4703c19
cpraa/.git/objects/17/01fe9a1d3f7dccef51c183adf81a35cdcf7720
cpraa/.git/objects/1a/06c236c320243f9adb6072fdbdcabbd66cd08f
cpraa/.git/objects/1b/a340088c03e05f6cf5de90e98ef65e30aea06c
cpraa/.git/objects/21/7f355ca7bf0521b80d19f67c43dda7be25da7a
cpraa/.git/objects/21/d3ca2a62284c7ee9ef8fe4dee91161c5a64151
cpraa/.git/objects/2d/a7baea713fe3e70375fabbf2428518231bae51
cpraa/.git/objects/2e/0258c159e36e1b236854b4f0ab7c74d5ac590e
cpraa/.git/objects/31/fa8833de3948234f2d031dbd025068af5af650
cpraa/.git/objects/34/a6e8b41599943a49cb68ffce5a9fb6386f1cae
cpraa/.git/objects/35/18f5b7d845f0903365e03225042057c4c40e92
cpraa/.git/objects/35/c180e8eba6389c93aacb1d6cbbefc8123a643f
cpraa/.git/objects/39/d10bf4f0ee43c5cd35ee613d5cc94598eda4b5
cpraa/.git/objects/39/e0f81ab691543d6d4ab6a29b673ab6ff86a878
cpraa/.git/objects/3a/747cd9009bc0987c29e955f4bc22bf50a52850
cpraa-0.8.1.dist-info/WHEEL
cpraa-0.8.1.dist-info/METADATA
cpraa-0.8.1.dist-info/RECORD
