Metadata-Version: 2.1
Name: cpraa
Version: 0.8.1
Summary: A checker for probabilistic abstract argumentation
Home-page: https://dgit.cs.uni-saarland.de/Nikolai/cpraa
License: MIT
Author: Nikolai Käfer
Author-email: nikolai.kaefer@tu-dresden.de
Maintainer: Nikolai Käfer
Maintainer-email: nikolai.kaefer@tu-dresden.de
Requires-Python: >=3.7,<4.0
Classifier: License :: OSI Approved :: MIT License
Classifier: Programming Language :: Python :: 3
Classifier: Programming Language :: Python :: 3.7
Classifier: Programming Language :: Python :: 3.8
Classifier: Programming Language :: Python :: 3.9
Requires-Dist: PySMT (>=0.9.0,<0.10.0)
Requires-Dist: cvxopt (>=1.2.5,<2.0.0)
Requires-Dist: matplotlib (>=3.3.4,<4.0.0)
Requires-Dist: numpy (>=1.20.0,<2.0.0)
Requires-Dist: pypoman (>=0.5.4,<0.6.0)
Requires-Dist: scipy (>=1.6.0,<2.0.0)
Requires-Dist: z3-solver (>=4.8.8,<5.0.0)
Project-URL: Repository, https://dgit.cs.uni-saarland.de/Nikolai/cpraa
